tensorlink/__init__.py
tensorlink/api/__init__.py
tensorlink/api/__pycache__/__init__.cpython-311.pyc
tensorlink/api/__pycache__/node.cpython-311.pyc
tensorlink/api/inference.py
tensorlink/api/node.py
tensorlink/config/SmartnodesCoordinator.json
tensorlink/config/SmartnodesCore.json
tensorlink/config/SmartnodesERC20.json
tensorlink/config/__init__.py
tensorlink/config/config.json
tensorlink/config/custom_install.py
tensorlink/config/models.json
tensorlink/crypto/__init__.py
tensorlink/crypto/__pycache__/__init__.cpython-311.pyc
tensorlink/crypto/__pycache__/__init__.cpython-312.pyc
tensorlink/crypto/__pycache__/__init__.cpython-39.pyc
tensorlink/crypto/__pycache__/rsa.cpython-311.pyc
tensorlink/crypto/__pycache__/rsa.cpython-312.pyc
tensorlink/crypto/__pycache__/rsa.cpython-39.pyc
tensorlink/crypto/rsa.py
tensorlink/ml/__init__.py
tensorlink/ml/__pycache__/__init__.cpython-311.pyc
tensorlink/ml/__pycache__/__init__.cpython-312.pyc
tensorlink/ml/__pycache__/__init__.cpython-39.pyc
tensorlink/ml/__pycache__/graphing.cpython-311.pyc
tensorlink/ml/__pycache__/module.cpython-311.pyc
tensorlink/ml/__pycache__/optim.cpython-311.pyc
tensorlink/ml/__pycache__/proofs.cpython-311.pyc
tensorlink/ml/__pycache__/shared_memory.cpython-311.pyc
tensorlink/ml/__pycache__/utils.cpython-311.pyc
tensorlink/ml/__pycache__/validator.cpython-311.pyc
tensorlink/ml/__pycache__/worker.cpython-311.pyc
tensorlink/ml/graphing.py
tensorlink/ml/module.py
tensorlink/ml/optim.py
tensorlink/ml/proofs.py
tensorlink/ml/testing/__init__.py
tensorlink/ml/testing/__pycache__/__init__.cpython-311.pyc
tensorlink/ml/testing/__pycache__/graphing.cpython-311.pyc
tensorlink/ml/testing/graphing.py
tensorlink/ml/testing/proof_of_learning.py
tensorlink/ml/utils.py
tensorlink/ml/validator.py
tensorlink/ml/worker.py
tensorlink/mpc/__init__.py
tensorlink/mpc/__pycache__/__init__.cpython-311.pyc
tensorlink/mpc/__pycache__/nodes.cpython-311.pyc
tensorlink/mpc/__pycache__/shared_memory.cpython-311.pyc
tensorlink-0.2.0.post1.dist-info/LICENSE
tensorlink-0.2.0.post1.dist-info/METADATA
tensorlink-0.2.0.post1.dist-info/WHEEL
tensorlink-0.2.0.post1.dist-info/RECORD
