Metadata-Version: 2.3
Name: tensorlink
Version: 0.2.0.post1
Summary: Tensorlink is a decentralized Python library for distributed PyTorch models, providing easy Hugging Face API access and enabling users to share compute resources across a global network.
License: MIT
Author: Smartnodes Lab
Author-email: smartnodes-lab@proton.me
Requires-Python: >=3.10,<4.0
Classifier: Development Status :: 3 - Alpha
Classifier: License :: OSI Approved :: MIT License
Classifier: Natural Language :: English
Classifier: Operating System :: MacOS
Classifier: Operating System :: Unix
Classifier: Programming Language :: Python :: 3
Classifier: Programming Language :: Python :: 3.10
Classifier: Programming Language :: Python :: 3.11
Classifier: Programming Language :: Python :: 3.12
Classifier: Programming Language :: Python :: 3.13
Requires-Dist: cryptography (>=45.0.3,<46.0.0)
Requires-Dist: fastapi (==0.115.11)
Requires-Dist: graphviz (==0.20.3)
Requires-Dist: huggingface-hub (>=0.32.3,<0.33.0)
Requires-Dist: matplotlib (==3.9.2)
Requires-Dist: miniupnpc (==2.2.8)
Requires-Dist: multiprocess (==0.70.16)
Requires-Dist: networkx (==3.2.1)
Requires-Dist: psutil (==7.0.0)
Requires-Dist: pydantic (==2.9.2)
Requires-Dist: pydantic-core (==2.23.4)
Requires-Dist: python-dotenv (==1.0.1)
Requires-Dist: regex (==2024.9.11)
Requires-Dist: requests (==2.32.3)
Requires-Dist: safetensors (==0.4.5)
Requires-Dist: tokenizers (>=0.21.1,<0.22.0)
Requires-Dist: torch (>=2.7.0,<3.0.0)
Requires-Dist: torchviz (==0.0.2)
Requires-Dist: tqdm (==4.66.5)
Requires-Dist: transformers (>=4.52.4,<5.0.0)
Requires-Dist: uvicorn (==0.34.0)
Requires-Dist: web3 (==7.3.0)
Project-URL: Documentation, https://smartnodes.ca/tensorlink/docs
Project-URL: Homepage, https://smartnodes.ca/tensorlink
Project-URL: Repository, https://github.com/smartnodes-lab/tensorlink
